mplsoccer/__about__.py
mplsoccer/__init__.py
mplsoccer/_pitch_base.py
mplsoccer/_pitch_plot.py
mplsoccer/bumpy_chart.py
mplsoccer/cm.py
mplsoccer/dimensions.py
mplsoccer/formations.py
mplsoccer/grid.py
mplsoccer/heatmap.py
mplsoccer/linecollection.py
mplsoccer/pitch.py
mplsoccer/py_pizza.py
mplsoccer/quiver.py
mplsoccer/radar_chart.py
mplsoccer/scatterutils.py
mplsoccer/statsbomb.py
mplsoccer/utils.py
mplsoccer-1.5.0.dist-info/METADATA
mplsoccer-1.5.0.dist-info/WHEEL
mplsoccer-1.5.0.dist-info/licenses/LICENSE
mplsoccer-1.5.0.dist-info/RECORD
