Metadata-Version: 2.4
Name: mplsoccer
Version: 1.5.0
Summary: Football pitch plotting library for matplotlib
Project-URL: Documentation, https://mplsoccer.readthedocs.io
Project-URL: Issues, https://github.com/andrewRowlinson/mplsoccer/issues
Project-URL: Source, https://github.com/andrewRowlinson/mplsoccer
Author-email: Andrew Rowlinson <rowlinsonandy@gmail.com>, Anmol Durgapal <slothfulwave10@gmail.com>
License-Expression: MIT
License-File: LICENSE
Keywords: football,matplotlib,mplsoccer,soccer,visualization
Classifier: Framework :: Matplotlib
Classifier: License :: OSI Approved :: MIT License
Classifier: Programming Language :: Python
Classifier: Programming Language :: Python :: 3.9
Classifier: Programming Language :: Python :: 3.10
Classifier: Programming Language :: Python :: 3.11
Classifier: Programming Language :: Python :: 3.12
Classifier: Programming Language :: Python :: 3.13
Classifier: Programming Language :: Python :: 3.14
Classifier: Topic :: Scientific/Engineering :: Visualization
Requires-Python: >=3.9
Requires-Dist: matplotlib>=3.6
Requires-Dist: numpy
Requires-Dist: pandas
Requires-Dist: pillow
Requires-Dist: requests
Requires-Dist: scipy
Requires-Dist: seaborn
